<?xml version="1.0" encoding="UTF-8"?>
<templates id="template" xml:space="preserve">
    <t t-name="pos_training_inherit.InheritPartnerDetailsEdit" t-inherit="point_of_sale.PartnerDetailsEdit" t-inherit-mode="extension" owl="1">
        <xpath expr="//div[hasclass('partner-details-left')]" position="inside">
            <div class="partner-detail">
                <span class="label">New Mobile Number</span>
                <input name="new_phone_number" t-model="changes.new_phone_number" t-on-change="captureChange"/>
            </div>
        </xpath>
    </t>
    <t t-name="pos_training.CustomerList" t-inherit="point_of_sale.PartnerListScreen" t-inherit-mode="extension" owl="1">
        <xpath expr="//table[hasclass('partner-list')]//tr//th[2]" position="after">
            <th>New Mobile Number</th>
        </xpath>
    </t>

    <t t-name="pos_training.CustomerLine" t-inherit="point_of_sale.PartnerLine" t-inherit-mode="extension" owl="1">
        <xpath expr="//tr//td[2]" position="after">
            <t t-if="props.partner.new_phone_number" t-out="props.partner.new_phone_number"/>
            <t t-else="">Not Available</t>

        </xpath>
    </t>
</templates>